subtitle_tool/__init__.py
subtitle_tool/ai.py
subtitle_tool/audio.py
subtitle_tool/cli.py
subtitle_tool/subtitles.py
subtitle_tool/utils.py
subtitle_tool-0.1.56.dist-info/METADATA
subtitle_tool-0.1.56.dist-info/WHEEL
subtitle_tool-0.1.56.dist-info/entry_points.txt
subtitle_tool-0.1.56.dist-info/licenses/LICENSE
subtitle_tool-0.1.56.dist-info/RECORD
