Metadata-Version: 2.4
Name: subtitle-tool
Version: 0.1.56
Summary: A tool for generating subtitles using Google Gemini models.
Project-URL: Homepage, https://github.com/jeduardo/subtitle-tool
Project-URL: Repository, https://github.com/jeduardo/subtitle-tool.git
Project-URL: Issues, https://github.com/jeduardo/subtitle-tool/issues
Author-email: "J. Eduardo" <contact@jeduardo.com>
License-Expression: MIT
License-File: LICENSE
Keywords: ai,audio,cli,gemini,google-gemini,srt,subtitles,video
Classifier: Development Status :: 4 - Beta
Classifier: License :: OSI Approved :: MIT License
Classifier: Programming Language :: Python :: 3.11
Requires-Python: >=3.13
Requires-Dist: audioop-lts>=0.2.1
Requires-Dist: click>=8.2.1
Requires-Dist: ffmpeg-python>=0.2.0
Requires-Dist: google-genai>=1.16.1
Requires-Dist: humanize>=4.12.3
Requires-Dist: pydub>=0.25.1
Requires-Dist: pysubs2>=1.8.0
Requires-Dist: srt-equalizer>=0.1.10
Requires-Dist: tenacity>=9.1.2
Provides-Extra: dev
Requires-Dist: pytest-cov>=6.1.1; extra == 'dev'
Requires-Dist: pytest>=8.4.0; extra == 'dev'
Requires-Dist: ruff>=0.12.0; extra == 'dev'
